{
  "summary": {
    "addressKey": "tampines-224-tampines-st-23",
    "town": "TAMPINES",
    "block": "224",
    "streetName": "TAMPINES ST 23",
    "coordinates": {
      "lat": 1.35538493501861,
      "lng": 103.95348853253
    },
    "medianPrice": 530000,
    "priceIqr": [
      530000,
      530000
    ],
    "pricePerSqmMedian": 5698.92,
    "pricePerSqftMedian": 529.45,
    "transactionCount": 1,
    "floorAreaRange": [
      67,
      98
    ],
    "leaseCommenceRange": [
      1985,
      1985
    ],
    "latestMonth": "2024-08",
    "availableDateRange": [
      "1992-07",
      "2024-08"
    ],
    "flatTypes": [
      "3 ROOM",
      "4 ROOM"
    ],
    "flatModels": [
      "NEW GENERATION",
      "MAX FLOOR 4"
    ],
    "nearestMrt": {
      "stationName": "TAMPINES EAST MRT STATION",
      "distanceMeters": 167
    }
  },
  "monthlyTrend": [
    {
      "month": "1992-07",
      "medianPrice": 79000,
      "transactionCount": 1,
      "medianPricePerSqm": 831.58
    },
    {
      "month": "1993-01",
      "medianPrice": 115000,
      "transactionCount": 1,
      "medianPricePerSqm": 1197.92
    },
    {
      "month": "1993-03",
      "medianPrice": 80000,
      "transactionCount": 1,
      "medianPricePerSqm": 860.22
    },
    {
      "month": "1993-07",
      "medianPrice": 120000,
      "transactionCount": 1,
      "medianPricePerSqm": 1237.11
    },
    {
      "month": "1993-09",
      "medianPrice": 101500,
      "transactionCount": 2,
      "medianPricePerSqm": 1227.84
    },
    {
      "month": "1994-02",
      "medianPrice": 150000,
      "transactionCount": 1,
      "medianPricePerSqm": 1612.9
    },
    {
      "month": "1994-05",
      "medianPrice": 153000,
      "transactionCount": 1,
      "medianPricePerSqm": 1681.32
    },
    {
      "month": "1995-01",
      "medianPrice": 89000,
      "transactionCount": 1,
      "medianPricePerSqm": 1328.36
    },
    {
      "month": "1995-06",
      "medianPrice": 230000,
      "transactionCount": 1,
      "medianPricePerSqm": 2421.05
    },
    {
      "month": "1995-12",
      "medianPrice": 150000,
      "transactionCount": 1,
      "medianPricePerSqm": 2054.79
    },
    {
      "month": "1996-02",
      "medianPrice": 277500,
      "transactionCount": 1,
      "medianPricePerSqm": 2890.63
    },
    {
      "month": "1996-07",
      "medianPrice": 273000,
      "transactionCount": 1,
      "medianPricePerSqm": 2935.48
    },
    {
      "month": "1996-10",
      "medianPrice": 263000,
      "transactionCount": 2,
      "medianPricePerSqm": 3220.19
    },
    {
      "month": "1996-11",
      "medianPrice": 330000,
      "transactionCount": 1,
      "medianPricePerSqm": 3548.39
    },
    {
      "month": "1996-12",
      "medianPrice": 340000,
      "transactionCount": 1,
      "medianPricePerSqm": 3505.15
    },
    {
      "month": "1997-01",
      "medianPrice": 350000,
      "transactionCount": 1,
      "medianPricePerSqm": 3763.44
    },
    {
      "month": "1997-02",
      "medianPrice": 200000,
      "transactionCount": 1,
      "medianPricePerSqm": 2739.73
    },
    {
      "month": "1997-04",
      "medianPrice": 310000,
      "transactionCount": 1,
      "medianPricePerSqm": 3406.59
    },
    {
      "month": "1997-05",
      "medianPrice": 304000,
      "transactionCount": 1,
      "medianPricePerSqm": 3268.82
    },
    {
      "month": "1997-07",
      "medianPrice": 340000,
      "transactionCount": 1,
      "medianPricePerSqm": 3469.39
    },
    {
      "month": "1998-08",
      "medianPrice": 247000,
      "transactionCount": 1,
      "medianPricePerSqm": 2655.91
    },
    {
      "month": "1998-12",
      "medianPrice": 266000,
      "transactionCount": 1,
      "medianPricePerSqm": 2800
    },
    {
      "month": "1999-03",
      "medianPrice": 143000,
      "transactionCount": 1,
      "medianPricePerSqm": 2134.33
    },
    {
      "month": "1999-05",
      "medianPrice": 239000,
      "transactionCount": 1,
      "medianPricePerSqm": 2626.37
    },
    {
      "month": "1999-08",
      "medianPrice": 161000,
      "transactionCount": 1,
      "medianPricePerSqm": 2402.99
    },
    {
      "month": "1999-09",
      "medianPrice": 212000,
      "transactionCount": 1,
      "medianPricePerSqm": 2904.11
    },
    {
      "month": "2000-04",
      "medianPrice": 164000,
      "transactionCount": 1,
      "medianPricePerSqm": 2447.76
    },
    {
      "month": "2000-07",
      "medianPrice": 250000,
      "transactionCount": 1,
      "medianPricePerSqm": 2604.17
    },
    {
      "month": "2000-11",
      "medianPrice": 199000,
      "transactionCount": 2,
      "medianPricePerSqm": 2420.84
    },
    {
      "month": "2001-12",
      "medianPrice": 226000,
      "transactionCount": 1,
      "medianPricePerSqm": 2430.11
    },
    {
      "month": "2002-11",
      "medianPrice": 213000,
      "transactionCount": 1,
      "medianPricePerSqm": 2173.47
    },
    {
      "month": "2002-12",
      "medianPrice": 214100,
      "transactionCount": 1,
      "medianPricePerSqm": 2302.15
    },
    {
      "month": "2003-10",
      "medianPrice": 145000,
      "transactionCount": 1,
      "medianPricePerSqm": 2164.18
    },
    {
      "month": "2004-03",
      "medianPrice": 169000,
      "transactionCount": 2,
      "medianPricePerSqm": 2522.39
    },
    {
      "month": "2004-05",
      "medianPrice": 210000,
      "transactionCount": 1,
      "medianPricePerSqm": 2876.71
    },
    {
      "month": "2004-09",
      "medianPrice": 194000,
      "transactionCount": 1,
      "medianPricePerSqm": 2895.52
    },
    {
      "month": "2006-03",
      "medianPrice": 220000,
      "transactionCount": 1,
      "medianPricePerSqm": 2365.59
    },
    {
      "month": "2006-07",
      "medianPrice": 220000,
      "transactionCount": 1,
      "medianPricePerSqm": 2365.59
    },
    {
      "month": "2006-10",
      "medianPrice": 169000,
      "transactionCount": 1,
      "medianPricePerSqm": 2522.39
    },
    {
      "month": "2006-11",
      "medianPrice": 164000,
      "transactionCount": 2,
      "medianPricePerSqm": 2447.76
    },
    {
      "month": "2007-12",
      "medianPrice": 230000,
      "transactionCount": 1,
      "medianPricePerSqm": 2473.12
    },
    {
      "month": "2009-03",
      "medianPrice": 268000,
      "transactionCount": 1,
      "medianPricePerSqm": 2881.72
    },
    {
      "month": "2010-04",
      "medianPrice": 262000,
      "transactionCount": 1,
      "medianPricePerSqm": 3910.45
    },
    {
      "month": "2010-10",
      "medianPrice": 342000,
      "transactionCount": 1,
      "medianPricePerSqm": 3677.42
    },
    {
      "month": "2010-11",
      "medianPrice": 275000,
      "transactionCount": 1,
      "medianPricePerSqm": 4104.48
    },
    {
      "month": "2013-06",
      "medianPrice": 345000,
      "transactionCount": 1,
      "medianPricePerSqm": 5149.25
    },
    {
      "month": "2016-03",
      "medianPrice": 391000,
      "transactionCount": 1,
      "medianPricePerSqm": 4204.3
    },
    {
      "month": "2016-08",
      "medianPrice": 385000,
      "transactionCount": 1,
      "medianPricePerSqm": 4230.77
    },
    {
      "month": "2018-09",
      "medianPrice": 320000,
      "transactionCount": 1,
      "medianPricePerSqm": 4776.12
    },
    {
      "month": "2018-11",
      "medianPrice": 328000,
      "transactionCount": 1,
      "medianPricePerSqm": 4895.52
    },
    {
      "month": "2019-08",
      "medianPrice": 315000,
      "transactionCount": 1,
      "medianPricePerSqm": 4701.49
    },
    {
      "month": "2021-02",
      "medianPrice": 406000,
      "transactionCount": 1,
      "medianPricePerSqm": 4229.17
    },
    {
      "month": "2023-02",
      "medianPrice": 500000,
      "transactionCount": 1,
      "medianPricePerSqm": 5376.34
    },
    {
      "month": "2024-08",
      "medianPrice": 530000,
      "transactionCount": 1,
      "medianPricePerSqm": 5698.92
    }
  ],
  "recentTransactions": [
    {
      "id": "tampines-224-tampines-st-23-2024-08-191557",
      "month": "2024-08",
      "flatType": "4 ROOM",
      "storeyRange": "01 TO 03",
      "floorAreaSqm": 93,
      "flatModel": "NEW GENERATION",
      "leaseCommenceDate": 1985,
      "remainingLease": "60 years 05 months",
      "resalePrice": 530000,
      "pricePerSqm": 5698.92,
      "pricePerSqft": 529.45
    },
    {
      "id": "tampines-224-tampines-st-23-2023-02-163130",
      "month": "2023-02",
      "flatType": "4 ROOM",
      "storeyRange": "04 TO 06",
      "floorAreaSqm": 93,
      "flatModel": "NEW GENERATION",
      "leaseCommenceDate": 1985,
      "remainingLease": "61 years 10 months",
      "resalePrice": 500000,
      "pricePerSqm": 5376.34,
      "pricePerSqft": 499.48
    },
    {
      "id": "tampines-224-tampines-st-23-2021-02-91817",
      "month": "2021-02",
      "flatType": "4 ROOM",
      "storeyRange": "01 TO 03",
      "floorAreaSqm": 96,
      "flatModel": "NEW GENERATION",
      "leaseCommenceDate": 1985,
      "remainingLease": "63 years 11 months",
      "resalePrice": 406000,
      "pricePerSqm": 4229.17,
      "pricePerSqft": 392.9
    },
    {
      "id": "tampines-224-tampines-st-23-2019-08-55937",
      "month": "2019-08",
      "flatType": "3 ROOM",
      "storeyRange": "01 TO 03",
      "floorAreaSqm": 67,
      "flatModel": "NEW GENERATION",
      "leaseCommenceDate": 1985,
      "remainingLease": "65 years 04 months",
      "resalePrice": 315000,
      "pricePerSqm": 4701.49,
      "pricePerSqft": 436.78
    },
    {
      "id": "tampines-224-tampines-st-23-2018-11-40195",
      "month": "2018-11",
      "flatType": "3 ROOM",
      "storeyRange": "01 TO 03",
      "floorAreaSqm": 67,
      "flatModel": "NEW GENERATION",
      "leaseCommenceDate": 1985,
      "remainingLease": "66 years 01 month",
      "resalePrice": 328000,
      "pricePerSqm": 4895.52,
      "pricePerSqft": 454.81
    },
    {
      "id": "tampines-224-tampines-st-23-2018-09-36341",
      "month": "2018-09",
      "flatType": "3 ROOM",
      "storeyRange": "01 TO 03",
      "floorAreaSqm": 67,
      "flatModel": "NEW GENERATION",
      "leaseCommenceDate": 1985,
      "remainingLease": "66 years 03 months",
      "resalePrice": 320000,
      "pricePerSqm": 4776.12,
      "pricePerSqft": 443.72
    },
    {
      "id": "tampines-224-tampines-st-23-2016-08-968586",
      "month": "2016-08",
      "flatType": "4 ROOM",
      "storeyRange": "04 TO 06",
      "floorAreaSqm": 91,
      "flatModel": "NEW GENERATION",
      "leaseCommenceDate": 1985,
      "remainingLease": "68",
      "resalePrice": 385000,
      "pricePerSqm": 4230.77,
      "pricePerSqft": 393.05
    },
    {
      "id": "tampines-224-tampines-st-23-2016-03-959657",
      "month": "2016-03",
      "flatType": "4 ROOM",
      "storeyRange": "01 TO 03",
      "floorAreaSqm": 93,
      "flatModel": "NEW GENERATION",
      "leaseCommenceDate": 1985,
      "remainingLease": "68",
      "resalePrice": 391000,
      "pricePerSqm": 4204.3,
      "pricePerSqft": 390.59
    },
    {
      "id": "tampines-224-tampines-st-23-2013-06-626784",
      "month": "2013-06",
      "flatType": "3 ROOM",
      "storeyRange": "01 TO 03",
      "floorAreaSqm": 67,
      "flatModel": "NEW GENERATION",
      "leaseCommenceDate": 1985,
      "remainingLease": "58 years",
      "resalePrice": 345000,
      "pricePerSqm": 5149.25,
      "pricePerSqft": 478.38
    },
    {
      "id": "tampines-224-tampines-st-23-2010-11-570628",
      "month": "2010-11",
      "flatType": "3 ROOM",
      "storeyRange": "01 TO 03",
      "floorAreaSqm": 67,
      "flatModel": "NEW GENERATION",
      "leaseCommenceDate": 1985,
      "remainingLease": "58 years",
      "resalePrice": 275000,
      "pricePerSqm": 4104.48,
      "pricePerSqft": 381.32
    },
    {
      "id": "tampines-224-tampines-st-23-2010-10-568397",
      "month": "2010-10",
      "flatType": "4 ROOM",
      "storeyRange": "04 TO 06",
      "floorAreaSqm": 93,
      "flatModel": "NEW GENERATION",
      "leaseCommenceDate": 1985,
      "remainingLease": "58 years",
      "resalePrice": 342000,
      "pricePerSqm": 3677.42,
      "pricePerSqft": 341.64
    },
    {
      "id": "tampines-224-tampines-st-23-2010-04-549161",
      "month": "2010-04",
      "flatType": "3 ROOM",
      "storeyRange": "04 TO 06",
      "floorAreaSqm": 67,
      "flatModel": "NEW GENERATION",
      "leaseCommenceDate": 1985,
      "remainingLease": "58 years",
      "resalePrice": 262000,
      "pricePerSqm": 3910.45,
      "pricePerSqft": 363.29
    },
    {
      "id": "tampines-224-tampines-st-23-2009-03-513646",
      "month": "2009-03",
      "flatType": "4 ROOM",
      "storeyRange": "01 TO 03",
      "floorAreaSqm": 93,
      "flatModel": "NEW GENERATION",
      "leaseCommenceDate": 1985,
      "remainingLease": "58 years",
      "resalePrice": 268000,
      "pricePerSqm": 2881.72,
      "pricePerSqft": 267.72
    },
    {
      "id": "tampines-224-tampines-st-23-2007-12-480149",
      "month": "2007-12",
      "flatType": "4 ROOM",
      "storeyRange": "01 TO 03",
      "floorAreaSqm": 93,
      "flatModel": "NEW GENERATION",
      "leaseCommenceDate": 1985,
      "remainingLease": "58 years",
      "resalePrice": 230000,
      "pricePerSqm": 2473.12,
      "pricePerSqft": 229.76
    },
    {
      "id": "tampines-224-tampines-st-23-2006-11-451133",
      "month": "2006-11",
      "flatType": "3 ROOM",
      "storeyRange": "01 TO 03",
      "floorAreaSqm": 67,
      "flatModel": "NEW GENERATION",
      "leaseCommenceDate": 1985,
      "remainingLease": "58 years",
      "resalePrice": 160000,
      "pricePerSqm": 2388.06,
      "pricePerSqft": 221.86
    },
    {
      "id": "tampines-224-tampines-st-23-2006-11-451134",
      "month": "2006-11",
      "flatType": "3 ROOM",
      "storeyRange": "01 TO 03",
      "floorAreaSqm": 67,
      "flatModel": "NEW GENERATION",
      "leaseCommenceDate": 1985,
      "remainingLease": "58 years",
      "resalePrice": 168000,
      "pricePerSqm": 2507.46,
      "pricePerSqft": 232.95
    },
    {
      "id": "tampines-224-tampines-st-23-2006-10-448831",
      "month": "2006-10",
      "flatType": "3 ROOM",
      "storeyRange": "01 TO 03",
      "floorAreaSqm": 67,
      "flatModel": "NEW GENERATION",
      "leaseCommenceDate": 1985,
      "remainingLease": "58 years",
      "resalePrice": 169000,
      "pricePerSqm": 2522.39,
      "pricePerSqft": 234.34
    },
    {
      "id": "tampines-224-tampines-st-23-2006-07-441864",
      "month": "2006-07",
      "flatType": "4 ROOM",
      "storeyRange": "04 TO 06",
      "floorAreaSqm": 93,
      "flatModel": "NEW GENERATION",
      "leaseCommenceDate": 1985,
      "remainingLease": "58 years",
      "resalePrice": 220000,
      "pricePerSqm": 2365.59,
      "pricePerSqft": 219.77
    },
    {
      "id": "tampines-224-tampines-st-23-2006-03-432353",
      "month": "2006-03",
      "flatType": "4 ROOM",
      "storeyRange": "01 TO 03",
      "floorAreaSqm": 93,
      "flatModel": "NEW GENERATION",
      "leaseCommenceDate": 1985,
      "remainingLease": "58 years",
      "resalePrice": 220000,
      "pricePerSqm": 2365.59,
      "pricePerSqft": 219.77
    },
    {
      "id": "tampines-224-tampines-st-23-2004-09-388112",
      "month": "2004-09",
      "flatType": "3 ROOM",
      "storeyRange": "01 TO 03",
      "floorAreaSqm": 67,
      "flatModel": "NEW GENERATION",
      "leaseCommenceDate": 1985,
      "remainingLease": "58 years",
      "resalePrice": 194000,
      "pricePerSqm": 2895.52,
      "pricePerSqft": 269
    }
  ]
}