{
  "summary": {
    "addressKey": "yishun-504a-yishun-st-51",
    "town": "YISHUN",
    "block": "504A",
    "streetName": "YISHUN ST 51",
    "displayName": "ACACIA BREEZE @ YISHUN",
    "coordinates": {
      "lat": 1.41807055182868,
      "lng": 103.844083330937
    },
    "medianPrice": 575000,
    "transactionCount": 9,
    "floorAreaRange": [
      68,
      112
    ],
    "leaseCommenceRange": [
      2014,
      2014
    ],
    "latestMonth": "2026-03",
    "availableDateRange": [
      "2019-09",
      "2026-03"
    ],
    "flatTypes": [
      "3 ROOM",
      "4 ROOM",
      "5 ROOM"
    ],
    "flatModels": [
      "IMPROVED",
      "MODEL A",
      "MAX FLOOR 13"
    ],
    "nearestMrt": {
      "stationName": "KHATIB MRT STATION",
      "distanceMeters": 1207
    },
    "nearbyMrts": [
      {
        "stationName": "KHATIB MRT STATION",
        "distanceMeters": 1207
      },
      {
        "stationName": "YISHUN MRT STATION",
        "distanceMeters": 1584
      },
      {
        "stationName": "CANBERRA MRT STATION",
        "distanceMeters": 3179
      }
    ],
    "priceIqr": [
      502888,
      638000
    ],
    "pricePerSqmMedian": 6934.78,
    "pricePerSqftMedian": 644.26
  },
  "monthlyTrend": [
    {
      "month": "2019-09",
      "medianPrice": 442500,
      "transactionCount": 2,
      "medianPricePerSqm": 4276.01
    },
    {
      "month": "2019-10",
      "medianPrice": 302000,
      "transactionCount": 1,
      "medianPricePerSqm": 4441.18
    },
    {
      "month": "2019-12",
      "medianPrice": 485000,
      "transactionCount": 2,
      "medianPricePerSqm": 4717.98
    },
    {
      "month": "2020-01",
      "medianPrice": 350000,
      "transactionCount": 5,
      "medianPricePerSqm": 4239.13
    },
    {
      "month": "2020-02",
      "medianPrice": 410000,
      "transactionCount": 3,
      "medianPricePerSqm": 4456.52
    },
    {
      "month": "2020-05",
      "medianPrice": 295000,
      "transactionCount": 1,
      "medianPricePerSqm": 4338.24
    },
    {
      "month": "2020-06",
      "medianPrice": 340000,
      "transactionCount": 1,
      "medianPricePerSqm": 3695.65
    },
    {
      "month": "2020-09",
      "medianPrice": 403500,
      "transactionCount": 1,
      "medianPricePerSqm": 4385.87
    },
    {
      "month": "2020-10",
      "medianPrice": 320000,
      "transactionCount": 1,
      "medianPricePerSqm": 4705.88
    },
    {
      "month": "2020-11",
      "medianPrice": 325000,
      "transactionCount": 1,
      "medianPricePerSqm": 4779.41
    },
    {
      "month": "2021-04",
      "medianPrice": 318000,
      "transactionCount": 1,
      "medianPricePerSqm": 4676.47
    },
    {
      "month": "2021-05",
      "medianPrice": 452000,
      "transactionCount": 1,
      "medianPricePerSqm": 4860.22
    },
    {
      "month": "2021-06",
      "medianPrice": 430000,
      "transactionCount": 1,
      "medianPricePerSqm": 4673.91
    },
    {
      "month": "2021-07",
      "medianPrice": 627500,
      "transactionCount": 1,
      "medianPricePerSqm": 5602.68
    },
    {
      "month": "2021-11",
      "medianPrice": 520000,
      "transactionCount": 1,
      "medianPricePerSqm": 5652.17
    },
    {
      "month": "2021-12",
      "medianPrice": 495000,
      "transactionCount": 1,
      "medianPricePerSqm": 5322.58
    },
    {
      "month": "2022-02",
      "medianPrice": 515000,
      "transactionCount": 1,
      "medianPricePerSqm": 5537.63
    },
    {
      "month": "2022-03",
      "medianPrice": 399000,
      "transactionCount": 2,
      "medianPricePerSqm": 5867.65
    },
    {
      "month": "2022-04",
      "medianPrice": 510000,
      "transactionCount": 1,
      "medianPricePerSqm": 5543.48
    },
    {
      "month": "2022-08",
      "medianPrice": 526000,
      "transactionCount": 2,
      "medianPricePerSqm": 5717.4
    },
    {
      "month": "2022-10",
      "medianPrice": 456000,
      "transactionCount": 1,
      "medianPricePerSqm": 4903.23
    },
    {
      "month": "2022-11",
      "medianPrice": 558000,
      "transactionCount": 1,
      "medianPricePerSqm": 6000
    },
    {
      "month": "2022-12",
      "medianPrice": 540000,
      "transactionCount": 1,
      "medianPricePerSqm": 5869.57
    },
    {
      "month": "2023-01",
      "medianPrice": 550000,
      "transactionCount": 1,
      "medianPricePerSqm": 5978.26
    },
    {
      "month": "2024-07",
      "medianPrice": 638000,
      "transactionCount": 1,
      "medianPricePerSqm": 6934.78
    },
    {
      "month": "2024-08",
      "medianPrice": 760000,
      "transactionCount": 1,
      "medianPricePerSqm": 6785.71
    },
    {
      "month": "2024-09",
      "medianPrice": 575000,
      "transactionCount": 1,
      "medianPricePerSqm": 6250
    },
    {
      "month": "2024-10",
      "medianPrice": 477500,
      "transactionCount": 2,
      "medianPricePerSqm": 7022.06
    },
    {
      "month": "2025-02",
      "medianPrice": 503888,
      "transactionCount": 1,
      "medianPricePerSqm": 7410.12
    },
    {
      "month": "2025-07",
      "medianPrice": 650000,
      "transactionCount": 1,
      "medianPricePerSqm": 7065.22
    },
    {
      "month": "2025-12",
      "medianPrice": 605000,
      "transactionCount": 1,
      "medianPricePerSqm": 6505.38
    },
    {
      "month": "2026-03",
      "medianPrice": 502888,
      "transactionCount": 1,
      "medianPricePerSqm": 7395.41
    }
  ],
  "recentTransactions": [
    {
      "id": "yishun-504a-yishun-st-51-2026-03-229263",
      "month": "2026-03",
      "flatType": "3 ROOM",
      "storeyRange": "07 TO 09",
      "floorAreaSqm": 68,
      "flatModel": "MODEL A",
      "leaseCommenceDate": 2016,
      "remainingLease": "89 years 01 month",
      "resalePrice": 502888,
      "pricePerSqm": 7395.41,
      "pricePerSqft": 687.06
    },
    {
      "id": "yishun-504a-yishun-st-51-2025-12-221612",
      "month": "2025-12",
      "flatType": "4 ROOM",
      "storeyRange": "07 TO 09",
      "floorAreaSqm": 93,
      "flatModel": "MODEL A",
      "leaseCommenceDate": 2016,
      "remainingLease": "89 years 03 months",
      "resalePrice": 605000,
      "pricePerSqm": 6505.38,
      "pricePerSqft": 604.37
    },
    {
      "id": "yishun-504a-yishun-st-51-2025-07-221598",
      "month": "2025-07",
      "flatType": "4 ROOM",
      "storeyRange": "13 TO 15",
      "floorAreaSqm": 92,
      "flatModel": "MODEL A",
      "leaseCommenceDate": 2016,
      "remainingLease": "89 years 09 months",
      "resalePrice": 650000,
      "pricePerSqm": 7065.22,
      "pricePerSqft": 656.38
    },
    {
      "id": "yishun-504a-yishun-st-51-2025-02-220850",
      "month": "2025-02",
      "flatType": "3 ROOM",
      "storeyRange": "07 TO 09",
      "floorAreaSqm": 68,
      "flatModel": "MODEL A",
      "leaseCommenceDate": 2016,
      "remainingLease": "90 years 02 months",
      "resalePrice": 503888,
      "pricePerSqm": 7410.12,
      "pricePerSqft": 688.42
    },
    {
      "id": "yishun-504a-yishun-st-51-2024-10-196628",
      "month": "2024-10",
      "flatType": "3 ROOM",
      "storeyRange": "04 TO 06",
      "floorAreaSqm": 68,
      "flatModel": "MODEL A",
      "leaseCommenceDate": 2016,
      "remainingLease": "90 years 06 months",
      "resalePrice": 470000,
      "pricePerSqm": 6911.76,
      "pricePerSqft": 642.12
    },
    {
      "id": "yishun-504a-yishun-st-51-2024-10-196637",
      "month": "2024-10",
      "flatType": "3 ROOM",
      "storeyRange": "07 TO 09",
      "floorAreaSqm": 68,
      "flatModel": "MODEL A",
      "leaseCommenceDate": 2016,
      "remainingLease": "90 years 06 months",
      "resalePrice": 485000,
      "pricePerSqm": 7132.35,
      "pricePerSqft": 662.62
    },
    {
      "id": "yishun-504a-yishun-st-51-2024-09-196536",
      "month": "2024-09",
      "flatType": "4 ROOM",
      "storeyRange": "04 TO 06",
      "floorAreaSqm": 92,
      "flatModel": "MODEL A",
      "leaseCommenceDate": 2016,
      "remainingLease": "90 years 07 months",
      "resalePrice": 575000,
      "pricePerSqm": 6250,
      "pricePerSqft": 580.64
    },
    {
      "id": "yishun-504a-yishun-st-51-2024-08-196436",
      "month": "2024-08",
      "flatType": "5 ROOM",
      "storeyRange": "10 TO 12",
      "floorAreaSqm": 112,
      "flatModel": "IMPROVED",
      "leaseCommenceDate": 2016,
      "remainingLease": "90 years 08 months",
      "resalePrice": 760000,
      "pricePerSqm": 6785.71,
      "pricePerSqft": 630.41
    },
    {
      "id": "yishun-504a-yishun-st-51-2024-07-196253",
      "month": "2024-07",
      "flatType": "4 ROOM",
      "storeyRange": "10 TO 12",
      "floorAreaSqm": 92,
      "flatModel": "MODEL A",
      "leaseCommenceDate": 2016,
      "remainingLease": "90 years 08 months",
      "resalePrice": 638000,
      "pricePerSqm": 6934.78,
      "pricePerSqft": 644.26
    },
    {
      "id": "yishun-504a-yishun-st-51-2023-01-167486",
      "month": "2023-01",
      "flatType": "4 ROOM",
      "storeyRange": "10 TO 12",
      "floorAreaSqm": 92,
      "flatModel": "MODEL A",
      "leaseCommenceDate": 2016,
      "remainingLease": "92 years 03 months",
      "resalePrice": 550000,
      "pricePerSqm": 5978.26,
      "pricePerSqft": 555.4
    },
    {
      "id": "yishun-504a-yishun-st-51-2022-12-143357",
      "month": "2022-12",
      "flatType": "4 ROOM",
      "storeyRange": "07 TO 09",
      "floorAreaSqm": 92,
      "flatModel": "MODEL A",
      "leaseCommenceDate": 2016,
      "remainingLease": "92 years 05 months",
      "resalePrice": 540000,
      "pricePerSqm": 5869.57,
      "pricePerSqft": 545.3
    },
    {
      "id": "yishun-504a-yishun-st-51-2022-11-143198",
      "month": "2022-11",
      "flatType": "4 ROOM",
      "storeyRange": "10 TO 12",
      "floorAreaSqm": 93,
      "flatModel": "MODEL A",
      "leaseCommenceDate": 2016,
      "remainingLease": "92 years 05 months",
      "resalePrice": 558000,
      "pricePerSqm": 6000,
      "pricePerSqft": 557.42
    },
    {
      "id": "yishun-504a-yishun-st-51-2022-10-143000",
      "month": "2022-10",
      "flatType": "4 ROOM",
      "storeyRange": "01 TO 03",
      "floorAreaSqm": 93,
      "flatModel": "MODEL A",
      "leaseCommenceDate": 2016,
      "remainingLease": "92 years 06 months",
      "resalePrice": 456000,
      "pricePerSqm": 4903.23,
      "pricePerSqft": 455.53
    },
    {
      "id": "yishun-504a-yishun-st-51-2022-08-142664",
      "month": "2022-08",
      "flatType": "4 ROOM",
      "storeyRange": "04 TO 06",
      "floorAreaSqm": 92,
      "flatModel": "MODEL A",
      "leaseCommenceDate": 2016,
      "remainingLease": "92 years 07 months",
      "resalePrice": 515000,
      "pricePerSqm": 5597.83,
      "pricePerSqft": 520.06
    },
    {
      "id": "yishun-504a-yishun-st-51-2022-08-142679",
      "month": "2022-08",
      "flatType": "4 ROOM",
      "storeyRange": "10 TO 12",
      "floorAreaSqm": 92,
      "flatModel": "MODEL A",
      "leaseCommenceDate": 2016,
      "remainingLease": "92 years 08 months",
      "resalePrice": 537000,
      "pricePerSqm": 5836.96,
      "pricePerSqft": 542.27
    },
    {
      "id": "yishun-504a-yishun-st-51-2022-04-141978",
      "month": "2022-04",
      "flatType": "4 ROOM",
      "storeyRange": "10 TO 12",
      "floorAreaSqm": 92,
      "flatModel": "MODEL A",
      "leaseCommenceDate": 2016,
      "remainingLease": "92 years 11 months",
      "resalePrice": 510000,
      "pricePerSqm": 5543.48,
      "pricePerSqft": 515.01
    },
    {
      "id": "yishun-504a-yishun-st-51-2022-03-141767",
      "month": "2022-03",
      "flatType": "3 ROOM",
      "storeyRange": "07 TO 09",
      "floorAreaSqm": 68,
      "flatModel": "MODEL A",
      "leaseCommenceDate": 2016,
      "remainingLease": "93 years",
      "resalePrice": 398000,
      "pricePerSqm": 5852.94,
      "pricePerSqft": 543.76
    },
    {
      "id": "yishun-504a-yishun-st-51-2022-03-141775",
      "month": "2022-03",
      "flatType": "3 ROOM",
      "storeyRange": "07 TO 09",
      "floorAreaSqm": 68,
      "flatModel": "MODEL A",
      "leaseCommenceDate": 2016,
      "remainingLease": "93 years 01 month",
      "resalePrice": 400000,
      "pricePerSqm": 5882.35,
      "pricePerSqft": 546.49
    },
    {
      "id": "yishun-504a-yishun-st-51-2022-02-141686",
      "month": "2022-02",
      "flatType": "4 ROOM",
      "storeyRange": "10 TO 12",
      "floorAreaSqm": 93,
      "flatModel": "MODEL A",
      "leaseCommenceDate": 2016,
      "remainingLease": "93 years 02 months",
      "resalePrice": 515000,
      "pricePerSqm": 5537.63,
      "pricePerSqft": 514.46
    },
    {
      "id": "yishun-504a-yishun-st-51-2021-12-116613",
      "month": "2021-12",
      "flatType": "4 ROOM",
      "storeyRange": "10 TO 12",
      "floorAreaSqm": 93,
      "flatModel": "MODEL A",
      "leaseCommenceDate": 2016,
      "remainingLease": "93 years 04 months",
      "resalePrice": 495000,
      "pricePerSqm": 5322.58,
      "pricePerSqft": 494.48
    }
  ]
}